TTTS/MonteCarloDecisionTreeClassifier.py
TTTS/MonteCarloRandomForestClassifier.py
TTTS/__init__.py
TTTS-0.0.15.dist-info/LICENSE
TTTS-0.0.15.dist-info/METADATA
TTTS-0.0.15.dist-info/WHEEL
TTTS-0.0.15.dist-info/top_level.txt
TTTS-0.0.15.dist-info/RECORD
