Metadata-Version: 2.1
Name: TTTS
Version: 0.0.15
Summary: TTTS: Tree Test Time Simulation for Enhancing Decision Tree Robustness Against Adversarial Examples
Author-email: Ofir Arbili <ofir.arbili@gmail.com>, Seffi Cohen <seffi@post.bgu.ac.il>
Project-URL: Homepage, https://github.com/OArbili/TTTS
Project-URL: Issues, https://github.com/OArbili/TTTS/issues
Classifier: Programming Language :: Python :: 3
Classifier: License :: OSI Approved :: MIT License
Classifier: Operating System :: OS Independent
Requires-Python: >=3.8
License-File: LICENSE
